dagster_kafka/__init__.py
dagster_kafka/avro_io_manager.py
dagster_kafka/component.py
dagster_kafka/dlq.py
dagster_kafka/io_manager.py
dagster_kafka/json_schema_io_manager.py
dagster_kafka/monitoring.py
dagster_kafka/performance.py
dagster_kafka/production_utils.py
dagster_kafka/protobuf_io_manager.py
dagster_kafka/resources.py
dagster_kafka/resources_backup.py
dagster_kafka/schema_evolution.py
dagster_kafka/connect/__init__.py
dagster_kafka/connect/assets.py
dagster_kafka/connect/cli.py
dagster_kafka/connect/client.py
dagster_kafka/connect/resource.py
dagster_kafka/connect/sensors.py
dagster_kafka/dlq_tools/__init__.py
dagster_kafka/dlq_tools/dlq_alerts.py
dagster_kafka/dlq_tools/dlq_dashboard.py
dagster_kafka/dlq_tools/dlq_inspector.py
dagster_kafka/dlq_tools/dlq_monitor.py
dagster_kafka/dlq_tools/dlq_replayer.py
dagster_kafka-1.3.1.dist-info/licenses/LICENSE
dagster_kafka-1.3.1.dist-info/METADATA
dagster_kafka-1.3.1.dist-info/WHEEL
dagster_kafka-1.3.1.dist-info/entry_points.txt
dagster_kafka-1.3.1.dist-info/top_level.txt
dagster_kafka-1.3.1.dist-info/RECORD
