Metadata-Version: 2.4
Name: dagster-kafka
Version: 1.3.1
Summary: Enterprise-grade Kafka integration for Dagster with Confluent Connect, comprehensive serialization support, DLQ handling, and production monitoring
Home-page: https://github.com/kingsley-123/dagster-kafka-integration
Author: Kingsley Okonkwo
Author-email: kingskonk@gmail.com
Maintainer: Kingsley Okonkwo
Maintainer-email: kingskonk@gmail.com
License: Apache-2.0
Project-URL: Homepage, https://github.com/kingsley-123/dagster-kafka-integration
Project-URL: Documentation, https://github.com/kingsley-123/dagster-kafka-integration/blob/main/README.md
Project-URL: Repository, https://github.com/kingsley-123/dagster-kafka-integration
Project-URL: Bug Reports, https://github.com/kingsley-123/dagster-kafka-integration/issues
Project-URL: Source, https://github.com/kingsley-123/dagster-kafka-integration
Project-URL: PyPI, https://pypi.org/project/dagster-kafka/
Keywords: dagster,kafka,apache-kafka,streaming,data-engineering,data-pipeline,etl,data-processing,json,json-schema,avro,protobuf,serialization,enterprise,production,monitoring,alerting,dlq,dead-letter-queue,error-handling,circuit-breaker,microservices,distributed-systems,real-time,schema-registry,confluent,data-validation,sasl,ssl,security,authentication,authorization,confluent-connect,kafka-connect,connectors,cdc
Platform: any
Classifier: Development Status :: 5 - Production/Stable
Classifier: Intended Audience :: Developers
Classifier: Intended Audience :: Information Technology
Classifier: Intended Audience :: System Administrators
Classifier: Topic :: Software Development :: Libraries :: Python Modules
Classifier: Topic :: System :: Distributed Computing
Classifier: Topic :: System :: Monitoring
Classifier: Topic :: Database
Classifier: Topic :: Internet
Classifier: License :: OSI Approved :: Apache Software License
Classifier: Programming Language :: Python
Classifier: Programming Language :: Python :: 3
Classifier: Programming Language :: Python :: 3.9
Classifier: Programming Language :: Python :: 3.10
Classifier: Programming Language :: Python :: 3.11
Classifier: Programming Language :: Python :: 3.12
Classifier: Programming Language :: Python :: 3 :: Only
Classifier: Operating System :: OS Independent
Classifier: Operating System :: POSIX
Classifier: Operating System :: Microsoft :: Windows
Classifier: Operating System :: MacOS
Classifier: Environment :: Console
Classifier: Environment :: No Input/Output (Daemon)
Classifier: Natural Language :: English
Provides: dagster_kafka
Requires-Python: >=3.9
License-File: LICENSE
Requires-Dist: dagster>=1.5.0
Requires-Dist: kafka-python>=2.0.2
Requires-Dist: fastavro>=1.8.0
Requires-Dist: confluent-kafka[avro]>=2.1.0
Requires-Dist: requests>=2.28.0
Requires-Dist: protobuf<6.0,>=4.21.0
Requires-Dist: grpcio-tools>=1.50.0
Requires-Dist: googleapis-common-protos>=1.56.0
Requires-Dist: jsonschema>=4.0.0
Provides-Extra: dev
Requires-Dist: pytest>=7.0.0; extra == "dev"
Requires-Dist: pytest-cov>=4.0.0; extra == "dev"
Requires-Dist: black>=22.0.0; extra == "dev"
Requires-Dist: isort>=5.10.0; extra == "dev"
Requires-Dist: flake8>=5.0.0; extra == "dev"
Requires-Dist: mypy>=1.0.0; extra == "dev"
Provides-Extra: docs
Requires-Dist: sphinx>=5.0.0; extra == "docs"
Requires-Dist: sphinx-rtd-theme>=1.0.0; extra == "docs"
Requires-Dist: myst-parser>=0.18.0; extra == "docs"
Provides-Extra: monitoring
Requires-Dist: prometheus-client>=0.14.0; extra == "monitoring"
Requires-Dist: slack-sdk>=3.19.0; extra == "monitoring"
Dynamic: author
Dynamic: author-email
Dynamic: classifier
Dynamic: description
Dynamic: description-content-type
Dynamic: home-page
Dynamic: keywords
Dynamic: license
Dynamic: license-file
Dynamic: maintainer
Dynamic: maintainer-email
Dynamic: platform
Dynamic: project-url
Dynamic: provides
Dynamic: provides-extra
Dynamic: requires-dist
Dynamic: requires-python
Dynamic: summary
